job_orchestration/Config.py
job_orchestration/Constants.py
job_orchestration/Loggers.py
job_orchestration/ProgressReporting.py
job_orchestration/SetConfigFilesReady.py
job_orchestration/StatusTracker.py
job_orchestration/TaskBase.py
job_orchestration/Worker.py
job_orchestration/__init__.py
job_orchestration/__main__.py
job_orchestration/clientUtils.py
job_orchestration/configBase.py
job_orchestration/getClientMethods.py
job_orchestration/rereadyFailedConfigs.py
job_orchestration/setupOutput.py
job_orchestration/specialTasks.py
job_orchestration/utils.py
job_orchestration/validation.py
job_orchestration/workerRegistration.py
job_orchestration/hyperparameter_optimisation/__init__.py
job_orchestration/hyperparameter_optimisation/base.py
job_orchestration/hyperparameter_optimisation/grid.py
job_orchestration/hyperparameter_optimisation/hypeparamaterOptimisationMethods.py
job_orchestration-0.0.7.dist-info/LICENSE
job_orchestration-0.0.7.dist-info/METADATA
job_orchestration-0.0.7.dist-info/WHEEL
job_orchestration-0.0.7.dist-info/top_level.txt
job_orchestration-0.0.7.dist-info/RECORD
