Metadata-Version: 2.1
Name: job-orchestration
Version: 0.0.7
Summary: Simple Orchestration for running a set of jobs each of which consist of a set of tasks.
Home-page: https://github.com/jamesHargreaves12/JobOrchestration
Author: James Hargreaves
Author-email: jameshargreaves12@gmail.com
Classifier: Programming Language :: Python :: 3
Classifier: License :: OSI Approved :: MIT License
Classifier: Operating System :: OS Independent
Requires-Python: >=3.7
License-File: LICENSE
Requires-Dist: fasteners (>=0.17)
Requires-Dist: GitPython (>=3.1)
